sqlbite/P1.py
sqlbite/P10.py
sqlbite/P2.py
sqlbite/P3.py
sqlbite/P4.py
sqlbite/P5.py
sqlbite/P6.py
sqlbite/P7.py
sqlbite/P8.py
sqlbite/P9.py
sqlbite/__init__.py
sqlbite-0.1.dist-info/licenses/LICENCE.txt
sqlbite-0.1.dist-info/METADATA
sqlbite-0.1.dist-info/WHEEL
sqlbite-0.1.dist-info/top_level.txt
sqlbite-0.1.dist-info/RECORD
