Metadata-Version: 2.4
Name: sqlbite
Version: 0.1
Summary: Powerful data structures for data analysis, time series, and statistics
Author: <justin mark
Author-email: The SQLbite Development Team <sqlbite-dev@python.org>
Classifier: Programming Language :: Python :: 3
Classifier: License :: OSI Approved :: MIT License
Classifier: Operating System :: OS Independent
License-File: LICENCE.txt
Dynamic: author
Dynamic: author-email
Dynamic: classifier
Dynamic: license-file
Dynamic: summary
